synamic/__init__.py
synamic/core/__init__.py
synamic/core/dependency_resolver.py
synamic/core/enums.py
synamic/core/synamic.py
synamic/core/synamic_config.py
synamic/core/builtin_event_handlers/__init__.py
synamic/core/builtin_event_handlers/handlers.py
synamic/core/classes/__init__.py
synamic/core/classes/filter_content.py
synamic/core/classes/frontmatter.py
synamic/core/classes/mapping.py
synamic/core/classes/path_tree.py
synamic/core/classes/static.py
synamic/core/classes/syml.py
synamic/core/classes/template_tags.py
synamic/core/classes/url.py
synamic/core/classes/utils.py
synamic/core/classes/virtual_file.py
synamic/core/contracts/__init__.py
synamic/core/contracts/cfields.py
synamic/core/contracts/content.py
synamic/core/contracts/data.py
synamic/core/contracts/document.py
synamic/core/contracts/fs_backend.py
synamic/core/contracts/host.py
synamic/core/contracts/module.py
synamic/core/contracts/site.py
synamic/core/contracts/synamic.py
synamic/core/contracts/url.py
synamic/core/default_data/__init__.py
synamic/core/default_data/_manager.py
synamic/core/default_data/configs.syd
synamic/core/default_data/content.model
synamic/core/default_data/dirs.syd
synamic/core/default_data/settings.syd
synamic/core/event_system/__init__.py
synamic/core/event_system/event_types.py
synamic/core/event_system/events.py
synamic/core/exceptions/__init__.py
synamic/core/exceptions/synamic_exceptions.py
synamic/core/functions/__init__.py
synamic/core/functions/date_time.py
synamic/core/functions/decorators.py
synamic/core/functions/frontmatter.py
synamic/core/functions/logging.py
synamic/core/functions/md.py
synamic/core/functions/normalizers.py
synamic/core/functions/query_compiler.py
synamic/core/functions/utils.py
synamic/core/functions/yaml_processor.py
synamic/core/new_filter/__init__.py
synamic/core/new_filter/filter_functions.py
synamic/core/new_parsers/__init__.py
synamic/core/new_parsers/document_parser.py
synamic-0.7.1.dev7.dist-info/METADATA
synamic-0.7.1.dev7.dist-info/RECORD
synamic-0.7.1.dev7.dist-info/WHEEL
synamic-0.7.1.dev7.dist-info/entry_points.txt
synamic-0.7.1.dev7.dist-info/top_level.txt
