Metadata-Version: 2.1
Name: synamic
Version: 0.7.1.dev7
Summary: Synamic
Home-page: https://github.com/SabujXi/Synamic
Author: Md. Sabuj Sarker
Author-email: md.sabuj.sarker@gmail.com
License: UNKNOWN
Platform: UNKNOWN
Requires-Python: >=3.6
Requires-Dist: Jinja2 (>=2.10)
Requires-Dist: MarkupSafe (>=1.0)
Requires-Dist: mistune (>=0.8.3)
Requires-Dist: Pillow (>=5.2.0)
Requires-Dist: sly (>=0.3)
Requires-Dist: aiohttp (>=3.4.4)
